README.rst
setup.py
smtpd_tls.py
smtpd_tls.egg-info/PKG-INFO
smtpd_tls.egg-info/SOURCES.txt
smtpd_tls.egg-info/dependency_links.txt
smtpd_tls.egg-info/top_level.txt