Metadata-Version: 1.1
Name: smtpd-tls
Version: 0.1
Summary: An extension to the standard python 2.x smtpd library implementing implicit/explicit SSL/TLS/STARTTLS
Home-page: https://github.com/tintinweb/python-smtpd-tls
Author: tintinweb
Author-email: tintinweb@oststrom.com
License: UNKNOWN
Download-URL: https://github.com/tintinweb/python-smtpd-tls/tarball/v0.1
Keywords: smtpd,starttls,tls,ssl
Platform: UNKNOWN
